{
  "OPEN_BROWSER": {
    "команда для відкриття посилання": "посилання(можна створити декілька)"
  },
  "POWER_OFF": {
    "команда для виключення пк": ""
  },
  "OPEN_FILES": {
    "команда для запуску папки": "шлях до папки(можна створити декілька)"
  },
  "CHECK_WEATHER": {
    "команда для того щоб дізнатись погоду в місті": "місто(можна створити декілька)"
  },
  "DO_SCREENSHOT": {
    "команда для створення скріншоту": ""
  },
  "ADD_SOUND": {
    "команда для збільшення звуку": "кількість(можна створити декілька)"
  },
  "REDUCE_SOUND": {
    "команда для зменьшення звуку": "кількість(можна створити декілька)"
  },
  "CURRENT_WINDOW": {
    "команда для закриття вікна": "закрить",
    "команда для того щоб заховати вікна": "заховать"
  },
  "START_APP": {
    "команда для запуску додатка": "шлях до додатку(можна до ярлика)(можна створити декілька)"
  },
  "CONNECT_WI_FI": {
    "команда для підключення": "назва мережі(можна створити декілька)"
  },
  "CHANGE_WINDOW": {
    "команда на відкриття вікна": "назва додатку(обов'язково з .exe)(можна створити декілька)"
  },
  "WORK_TEXT": {
    "команда для копіювання": "ctrl + c",
    "команда для перекладу": "переклади"
  }
}